CHANGELOG.md
LICENSE
MANIFEST.in
README.md
nagios2trac.py
setup.py
nagios2trac.egg-info/PKG-INFO
nagios2trac.egg-info/SOURCES.txt
nagios2trac.egg-info/dependency_links.txt
nagios2trac.egg-info/top_level.txt
rst/CHANGELOG.rst
rst/README.rst