Metadata-Version: 1.0
Name: nagios2trac
Version: 0.5.1
Summary: Let Nagios Create or Comment on Trac Tickets
Home-page: https://github.com/Jimdo/nagios2trac
Author: Daniel Bonkowski
Author-email: bonko@jimdo.com
License: Apache
Platform: UNKNOWN
